bgem/__init__.py
bgem/exceptions.py
bgem/tools.py
bgem/transform.py
bgem/bspline/__init__.py
bgem/bspline/brep_writer.py
bgem/bspline/bspline.py
bgem/bspline/bspline_approx.py
bgem/bspline/bspline_plot.py
bgem/bspline/curve_point.py
bgem/bspline/isec_curv_surf_point.py
bgem/bspline/isec_curve.py
bgem/bspline/isec_curve_surf.py
bgem/bspline/isec_point.py
bgem/bspline/isec_surf_surf.py
bgem/bspline/surface_point.py
bgem/bspline/surface_point_set.py
bgem/external/__init__.py
bgem/external/undo.py
bgem/geometry/geometry.py
bgem/gmsh/field.py
bgem/gmsh/gmsh.py
bgem/gmsh/gmsh_exceptions.py
bgem/gmsh/gmsh_io.py
bgem/gmsh/heal_mesh.py
bgem/gmsh/options.py
bgem/polygons/__init__.py
bgem/polygons/aabb_lookup.py
bgem/polygons/decomp.py
bgem/polygons/idmap.py
bgem/polygons/merge.py
bgem/polygons/plot_polygons.py
bgem/polygons/point.py
bgem/polygons/polygon.py
bgem/polygons/polygons.py
bgem/polygons/segment.py
bgem/stochastic/__init__.py
bgem/stochastic/broken_plane.py
bgem/stochastic/dfn.py
bgem/stochastic/dfn_model.py
bgem/stochastic/fr_set.py
bgem/stochastic/frac_isec.py
bgem/stochastic/frac_plane.py
bgem/stochastic/fracture.py
bgem/stochastic/isec_conflict.py
bgem/stochastic/isec_plane_point.py
bgem/stochastic/ploting.py
bgem-0.3.0.dist-info/LICENSE
bgem-0.3.0.dist-info/METADATA
bgem-0.3.0.dist-info/WHEEL
bgem-0.3.0.dist-info/top_level.txt
bgem-0.3.0.dist-info/RECORD
