Metadata-Version: 2.1
Name: bgem
Version: 0.3.0
Summary: B-spline modelling CAD and meshing tools.
Home-page: https://github.com/geomop/bgem
Author: Jan Brezina
Author-email: jan.brezina@tul.cz
License: GPL 3.0
Download-URL: https://github.com/geomop/bgem/archive/v{__version__}.tar.gz
Platform: UNKNOWN
Classifier: Development Status :: 2 - Pre-Alpha
Classifier: License :: OSI Approved :: GNU General Public License v3 or later (GPLv3+)
Classifier: Programming Language :: Python :: 3
Classifier: Intended Audience :: Developers
Classifier: Intended Audience :: Science/Research
Classifier: Topic :: Scientific/Engineering
Requires-Python: >=3
License-File: LICENSE
Requires-Dist: numpy (>=1.13.4)
Requires-Dist: pandas
Requires-Dist: scipy
Requires-Dist: bih
Requires-Dist: gmsh (>=4.10.4)
